{
    "Changes": [
	{
		"LogName": "EdwinStrings",
		"Action": "EditData",
		"Target": "Strings/Schedules/EdwinPayne",
		"Entries": 
        {
            "RuneCircle.000": "{{i18n:edwin_strings.RuneCircle.000}}",
			"Spells.000": "{{i18n:edwin_strings.Spells.000}}",
			"Reading.000": "{{i18n:edwin_strings.Reading.000}}",
			"Reading.001": "{{i18n:edwin_strings.Reading.001}}",
			"Saloon.000": "{{i18n:edwin_strings.Saloon.000}}",
			"Writing.000": "{{i18n:edwin_strings.Writing.000}}",

		}
	}
	]
}